deepmath/__init__.py
deepmath/base_classes/__init__.py
deepmath/base_classes/layer.py
deepmath/base_classes/network.py
deepmath/base_classes/optimizer.py
deepmath/layers/__init__.py
deepmath/layers/activation.py
deepmath/layers/dense.py
deepmath/layers/activation_functions/__init__.py
deepmath/layers/activation_functions/lrelu.py
deepmath/layers/activation_functions/relu.py
deepmath/layers/activation_functions/sigmoid.py
deepmath/layers/activation_functions/tanh.py
deepmath/optimizers/__init__.py
deepmath/optimizers/adam.py
deepmath/optimizers/momentum.py
deepmath/optimizers/rmsprop.py
deepmath/optimizers/sgd.py
deepmath-0.3.2.dist-info/LICENSE
deepmath-0.3.2.dist-info/METADATA
deepmath-0.3.2.dist-info/WHEEL
deepmath-0.3.2.dist-info/top_level.txt
deepmath-0.3.2.dist-info/RECORD
