Metadata-Version: 2.1
Name: deepmath
Version: 0.3.2
Summary: A machine learning library for educational purposes 
Home-page: https://github.com/mathraim/deepmath
Author: Raiymbek
Author-email: artmath1998@gmail.com
License: UNKNOWN
Download-URL: https://github.com/mathraim/deepmath/archive/0.0.2.tar.gz
Platform: UNKNOWN
Classifier: Programming Language :: Python :: 3
Classifier: Programming Language :: Python :: 3.6
Classifier: Programming Language :: Python :: 3.7
Classifier: License :: OSI Approved :: MIT License
Classifier: Operating System :: OS Independent
Requires-Dist: numpy
Requires-Dist: deepmath
